datautil/__init__.py
datautil/datautil.py
atd_data_util-0.1.0.dist-info/LICENSE
atd_data_util-0.1.0.dist-info/METADATA
atd_data_util-0.1.0.dist-info/WHEEL
atd_data_util-0.1.0.dist-info/top_level.txt
atd_data_util-0.1.0.dist-info/RECORD
