Metadata-Version: 2.1
Name: atd-data-util
Version: 0.1.0
Summary: Miscellaneous utilities for manipulating data.
Home-page: https://github.com/cityofaustin/atd-data-utilities/tree/master/atd-data-util
Author: City of Austin
Author-email: transportation.data@austintexas.gov
License: UNKNOWN
Platform: UNKNOWN
Classifier: Programming Language :: Python :: 3
Classifier: License :: Public Domain
Classifier: Operating System :: OS Independent
Classifier: Development Status :: 4 - Beta
Requires-Dist: requests
Requires-Dist: arrow
